salt_cloud_module_kamatera/__init__.py
salt_cloud_module_kamatera/loader.py
salt_cloud_module_kamatera/clouds/__init__.py
salt_cloud_module_kamatera/clouds/kamatera.py
salt_cloud_module_kamatera-0.0.3.dist-info/LICENSE
salt_cloud_module_kamatera-0.0.3.dist-info/METADATA
salt_cloud_module_kamatera-0.0.3.dist-info/WHEEL
salt_cloud_module_kamatera-0.0.3.dist-info/entry_points.txt
salt_cloud_module_kamatera-0.0.3.dist-info/top_level.txt
salt_cloud_module_kamatera-0.0.3.dist-info/RECORD
