Metadata-Version: 2.1
Name: salt-cloud-module-kamatera
Version: 0.0.3
Summary: SaltStack Cloud module for managing Kamatera compute resources
Home-page: https://github.com/Kamatera/salt-cloud-module-kamatera
Author: Kamatera
License: MIT
Platform: UNKNOWN
Requires-Dist: salt (>=2019.2.0)
